MANIFEST.in
board_association_view.xml
email_template.xml
event_data.xml
event_demo.xml
event_view.xml
res_partner_view.xml
setup.py
./__init__.py
./__openerp__.py
./event.py
./res_partner.py
./report/__init__.py
./report/report_event_registration.py
./wizard/__init__.py
./wizard/event_confirm.py
i18n/ar.po
i18n/bg.po
i18n/bs.po
i18n/ca.po
i18n/cs.po
i18n/da.po
i18n/de.po
i18n/el.po
i18n/es.po
i18n/es_AR.po
i18n/es_CR.po
i18n/es_EC.po
i18n/es_MX.po
i18n/es_VE.po
i18n/et.po
i18n/event.pot
i18n/fi.po
i18n/fr.po
i18n/gu.po
i18n/hi.po
i18n/hr.po
i18n/hu.po
i18n/id.po
i18n/it.po
i18n/ja.po
i18n/ko.po
i18n/lt.po
i18n/mk.po
i18n/mn.po
i18n/nb.po
i18n/nl.po
i18n/nl_BE.po
i18n/pl.po
i18n/pt.po
i18n/pt_BR.po
i18n/ro.po
i18n/ru.po
i18n/sk.po
i18n/sl.po
i18n/sq.po
i18n/sr.po
i18n/sr@latin.po
i18n/sv.po
i18n/tlh.po
i18n/tr.po
i18n/uk.po
i18n/vi.po
i18n/zh_CN.po
i18n/zh_TW.po
images/1_event_type_list.jpeg
images/2_events.jpeg
images/3_registrations.jpeg
images/events_kanban.jpeg
images/icon.png
openerp_event.egg-info/PKG-INFO
openerp_event.egg-info/SOURCES.txt
openerp_event.egg-info/dependency_links.txt
openerp_event.egg-info/requires.txt
openerp_event.egg-info/top_level.txt
report/report_event_registration_view.xml
security/event_security.xml
security/ir.model.access.csv
static/src/img/icon.png
test/process/event_draft2done.yml
test/ui/demo_data.yml
test/ui/duplicate_event.yml
wizard/event_confirm_view.xml